<!-- Maurya Empire (Revan) -->
<Root>
	<Entry>
		<zType/>
		<en-US/>
	</Entry>
	<Entry>
		<zType>TEXT_CITYNAME_MAURYA1</zType>
		<en-US>Pataliputra</en-US>
	</Entry>
	<Entry>
		<zType>TEXT_CITYNAME_MAURYA2</zType>
		<en-US>Kumhrar</en-US>
	</Entry>
	<Entry>
		<zType>TEXT_CITYNAME_MAURYA3</zType>
		<en-US>Punjab</en-US>
	</Entry>
	<Entry>
		<zType>TEXT_CITYNAME_MAURYA4</zType>
		<en-US>Bulandi Bagh</en-US>
	</Entry>
	<Entry>
		<zType>TEXT_CITYNAME_MAURYA5</zType>
		<en-US>Kamboja</en-US>
	</Entry>
	<Entry>
		<zType>TEXT_CITYNAME_MAURYA6</zType>
		<en-US>Magadha</en-US>
	</Entry>
	<Entry>
		<zType>TEXT_CITYNAME_MAURYA7</zType>
		<en-US>Gandhara</en-US>
	</Entry>
	<Entry>
		<zType>TEXT_CITYNAME_MAURYA8</zType>
		<en-US>Kashi</en-US>
	</Entry>
	<Entry>
		<zType>TEXT_CITYNAME_MAURYA9</zType>
		<en-US>Anga</en-US>
	</Entry>
	<Entry>
		<zType>TEXT_CITYNAME_MAURYA10</zType>
		<en-US>Taxila</en-US>
	</Entry>
	<Entry>
		<zType>TEXT_CITYNAME_MAURYA11</zType>
		<en-US>Chedi</en-US>
	</Entry>
	<Entry>
		<zType>TEXT_CITYNAME_MAURYA12</zType>
		<en-US>Kosala</en-US>
	</Entry>
	<Entry>
		<zType>TEXT_CITYNAME_MAURYA13</zType>
		<en-US>Kuru</en-US>
	</Entry>
	<Entry>
		<zType>TEXT_CITYNAME_MAURYA14</zType>
		<en-US>Malla</en-US>
	</Entry>
	<Entry>
		<zType>TEXT_CITYNAME_MAURYA15</zType>
		<en-US>Matsya</en-US>
	</Entry>
	<Entry>
		<zType>TEXT_CITYNAME_MAURYA16</zType>
		<en-US>Panchala</en-US>
	</Entry>
	<Entry>
		<zType>TEXT_CITYNAME_MAURYA17</zType>
		<en-US>Avanti</en-US>
	</Entry>
	<Entry>
		<zType>TEXT_CITYNAME_MAURYA18</zType>
		<en-US>Surasena</en-US>
	</Entry>
	<Entry>
		<zType>TEXT_CITYNAME_MAURYA19</zType>
		<en-US>Vajji</en-US>
	</Entry>
	<Entry>
		<zType>TEXT_CITYNAME_MAURYA20</zType>
		<en-US>Vatsa</en-US>
	</Entry>
</Root>
